README.rst
flask_wdb.py
setup.py
Flask_Wdb.egg-info/PKG-INFO
Flask_Wdb.egg-info/SOURCES.txt
Flask_Wdb.egg-info/dependency_links.txt
Flask_Wdb.egg-info/not-zip-safe
Flask_Wdb.egg-info/requires.txt
Flask_Wdb.egg-info/top_level.txt