Metadata-Version: 1.0
Name: Flask-Wdb
Version: 0.0.2
Summary: Integrate Wdb instead of Werkzeug debugger for Flask applications
Home-page: https://github.com/techniq/flask-wdb/
Author: Sean Lynch
Author-email: techniq35@gmail.com
License: BSD
Platform: any
Classifier: Development Status :: 3 - Alpha
Classifier: Intended Audience :: Developers
Classifier: License :: OSI Approved :: BSD License
Classifier: Operating System :: OS Independent
Classifier: Programming Language :: Python :: 2
Classifier: Topic :: Software Development :: Debuggers
